apache_manager/__init__.py
apache_manager/__main__.py
apache_manager/cli.py
apache_manager/exceptions.py
apache_manager/interactive.py
apache_manager/tests.py
apache_manager-2.2.dist-info/LICENSE.txt
apache_manager-2.2.dist-info/METADATA
apache_manager-2.2.dist-info/WHEEL
apache_manager-2.2.dist-info/entry_points.txt
apache_manager-2.2.dist-info/top_level.txt
apache_manager-2.2.dist-info/RECORD
