Metadata-Version: 2.1
Name: apache-manager
Version: 2.2
Summary: Monitor and control Apache web server workers from Python
Home-page: https://apache-manager.readthedocs.io
Author: Peter Odding
Author-email: peter@peterodding.com
License: MIT
Platform: UNKNOWN
Classifier: Development Status :: 4 - Beta
Classifier: Environment :: Console
Classifier: Intended Audience :: Developers
Classifier: Intended Audience :: Information Technology
Classifier: Intended Audience :: System Administrators
Classifier: License :: OSI Approved :: MIT License
Classifier: Natural Language :: English
Classifier: Programming Language :: Python
Classifier: Programming Language :: Python :: 2
Classifier: Programming Language :: Python :: 2.7
Classifier: Programming Language :: Python :: 3
Classifier: Programming Language :: Python :: 3.5
Classifier: Programming Language :: Python :: 3.6
Classifier: Programming Language :: Python :: 3.7
Classifier: Programming Language :: Python :: 3.8
Classifier: Programming Language :: Python :: Implementation :: CPython
Classifier: Programming Language :: Python :: Implementation :: PyPy
Classifier: Topic :: Internet :: WWW/HTTP :: HTTP Servers
Classifier: Topic :: Software Development
Classifier: Topic :: Software Development :: Libraries :: Python Modules
Classifier: Topic :: System :: Systems Administration
Classifier: Topic :: Terminals
Classifier: Topic :: Utilities
Requires-Dist: beautifulsoup4 (>=4.3.2)
Requires-Dist: coloredlogs (>=5.2)
Requires-Dist: humanfriendly (>=7.1.1)
Requires-Dist: proc (>=0.12)
Requires-Dist: property-manager (>=2.1)
Requires-Dist: six (>=1.9.0)
Requires-Dist: update-dotdee (>=5.0)
Requires-Dist: verboselogs (>=1.7)
